rahul.vivado-trafficlight.srcs/sources_1/new/trafficlight_controller.v
`timescale 1ns / 1ps
//////////////////////////////////////////////////////////////////////////////////
// Company: 
// Engineer: 
// 
// Create Date: 07/25/2025 11:18:46 AM
// Module Name: trafficlight_controller
// Project Name: traffic light controller
// Product family: Spartan-7
// Project part: xc7s50fgga484-1Q
// Target language: Verilog
// Simulator language: Mixed
// Target Simulator: Vivado Simulator
// Description: 
// 
// Dependencies: 
// 
// Revision:
// Revision 0.01 - File Created
// Additional Comments:
// 
//////////////////////////////////////////////////////////////////////////////////


module trafficlight_controller (
    input clock,
    input clear,
    input x,     // sensor 
    output reg [1:0] hwy,  
    output reg [1:0] road  
);

    localparam [1:0] RED = 2'b00,
                     GREEN = 2'b01,
                     YELLOW = 2'b10;
    
    localparam [2:0] S0 = 0,  // Highway green, Road red (default)
                     S1 = 1,  // Highway yellow, Road red
                     S2 = 2,  // Highway red, Road red (safety state)
                     S3 = 3,  // Highway red, Road green
                     S4 = 4;  // Highway red, Road yellow
    
    reg [2:0] state;
    reg [2:0] delay;

    always @(posedge clock) begin
        if (clear) begin
            state <= S0;  // Default state:Highway green
            delay <= 0;
        end
        else begin
            case (state)
                S0: begin  // Highway green
                    if (x)  // Car detected on road
                        state <= S1; // Start highway yellow
                end

                S1: begin  // Highway yellow
                    if (delay == 2) begin  // After 3 cycles
                        state <= S2;  // Go to red-red state
                        delay <= 0;   // Reset delay for next state
                    end
                    else
                        delay <= delay + 1;
                end

                S2: begin  // Red-red safety state
                    if (delay == 1) begin  // Wait 2 cycles
                        state <= S3;  // Switch to road green
                        delay <= 0;
                    end
                    else
                        delay <= delay + 1;
                end

                S3: begin  // Road green
                    if (!x)  // No car on road
                        state <= S4;  // Start road yellow
                end

                S4: begin  // Road yellow
                    if (delay == 2) begin  // After 3 cycles
                        state <= S0;  // Back to highway green
                        delay <= 0;
                    end
                    else
                        delay <= delay + 1;
                end

                default: state <= S0;  // Return to default state
            endcase
        end
    end

    always @(*) begin
        // Default state (Highway green, Road red)
        hwy = GREEN;
        road = RED;
        
        case (state)
            S0: begin  // Highway green
                hwy = GREEN;
                road = RED;
            end
            S1: begin  // Highway yellow
                hwy = YELLOW;
                road = RED;
            end
            S2: begin // All red (safety state)
                hwy = RED;
                road = RED;
            end
            S3: begin  // Road green
                hwy = RED;
                road = GREEN;
            end
            S4: begin  // Road yellow
                hwy = RED;
                road = YELLOW;
            end
        endcase
    end

endmodule

rahul.vivado-trafficlight.srcs/sim_1/new/trafficlight_tb.v
`timescale 1ns / 1ps
//////////////////////////////////////////////////////////////////////////////////
// Company: 
// Engineer: 
// 
// Create Date: 07/25/2025 11:19:17 AM
// Design Name: testbench
// Module Name: trafficlight_tb
// Project Name: traffic light controller
// Description: 
// 
// Dependencies: 
// 
// Revision:
// Revision 0.01 - File Created
// Additional Comments:
// 
//////////////////////////////////////////////////////////////////////////////////


module trafficlight_tb();
    reg CLOCK;    
    reg CLEAR;    
    reg X;        
    wire [1:0] HWY;   
    wire [1:0] ROAD;  

    reg [8*6:1] hwy_light, road_light;
    reg [8*11:1] state_name; 
    
    always @(*) begin
        case (uut.state)
            0: state_name = "HWY_GREEN";
            1: state_name = "HWY_YELLOW";
            2: state_name = "ALL_RED";
            3: state_name = "ROAD_GREEN";
            4: state_name = "ROAD_YELLOW";
            default: state_name = "UNKNOWN";
        endcase
        
        case (HWY)
            2'b00: hwy_light = "RED";
            2'b01: hwy_light = "GREEN";
            2'b10: hwy_light = "YELLOW";
            default: hwy_light = "ERROR";
        endcase
        
        case (ROAD)
            2'b00: road_light = "RED";
            2'b01: road_light = "GREEN";
            2'b10: road_light = "YELLOW";
            default: road_light = "ERROR";
        endcase
    end

    // Instantiate traffic controller
    trafficlight_controller uut (
        .clock(CLOCK),
        .clear(CLEAR),
          .x(X),
          .hwy(HWY),
        .road(ROAD)
    );

   initial CLOCK = 0;
   always #5 CLOCK = ~CLOCK;

    // Test stimulation
    initial begin

        $dumpfile("dump.vcd");
        $dumpvars(0, trafficlight_tb);

        // Test 1: Reset - Should go to HWY_GREEN
        $display("\nTest 1: Reset condition");
        CLEAR = 1;
        X = 0;
        #20;

        // Test 2: Normal operation - Highway Green
        $display("\nTest 2: Normal operation - Highway Green");
        CLEAR = 0;
        X = 0;
        #40;

        // Test 3: Car arrives - Transition through all states
        $display("\nTest 3: Car arrives - Full state transition");
        X = 1;  // Car arrives on road
        #150;  

        // Test 4: Car leaves - Transition back to Highway
        $display("\nTest 4: Car leaves - Return to Highway");
        X = 0;  // Car leaves
        #150;   

        // Test 5: Quick car detection
        $display("\nTest 5: Quick car detection");
        X= 1;  // Another car arrives
        #50;
        X= 0;  // Car leaves quickly
        #100;

        $finish;
    end

    always @(posedge CLOCK) begin
        $display("Time=%0t State=%s HWY=%s ROAD=%s CAR=%b", 
                 $time, state_name, hwy_light, road_light, X);
    end
endmodule

dump.vcd
$date
	Sat Mar 28 11:53:30 2026
$end
$version
	Icarus Verilog
$end
$timescale
	1ps
$end
$scope module trafficlight_tb $end
$var wire 2 ! ROAD [1:0] $end
$var wire 2 " HWY [1:0] $end
$var reg 1 # CLEAR $end
$var reg 1 $ CLOCK $end
$var reg 1 % X $end
$var reg 48 & hwy_light [48:1] $end
$var reg 48 ' road_light [48:1] $end
$var reg 88 ( state_name [88:1] $end
$scope module uut $end
$var wire 1 # clear $end
$var wire 1 $ clock $end
$var wire 1 % x $end
$var parameter 2 ) GREEN $end
$var parameter 2 * RED $end
$var parameter 3 + S0 $end
$var parameter 3 , S1 $end
$var parameter 3 - S2 $end
$var parameter 3 . S3 $end
$var parameter 3 / S4 $end
$var parameter 2 0 YELLOW $end
$var reg 3 1 delay [2:0] $end
$var reg 2 2 hwy [1:0] $end
$var reg 2 3 road [1:0] $end
$var reg 3 4 state [2:0] $end
$upscope $end
$upscope $end
$enddefinitions $end
$comment Show the parameter values. $end
$dumpall
b10 0
b100 /
b11 .
b10 -
b1 ,
b0 +
b0 *
b1 )
$end
#0
$dumpvars
bx 4
bx 3
bx 2
bx 1
bx (
bx '
bx &
0%
0$
1#
bx "
bx !
$end
#5000
b0 !
b0 3
b1 "
b1 2
b10100100100010101000100 '
b100011101010010010001010100010101001110 &
b10010000101011101011001010111110100011101010010010001010100010101001110 (
b0 1
b0 4
1$
#10000
0$
#15000
1$
#20000
0$
0#
#25000
1$
#30000
0$
#35000
1$
#40000
0$
#45000
1$
#50000
0$
#55000
1$
#60000
0$
1%
#65000
b10110010100010101001100010011000100111101010111 &
b10 "
b10 2
b1001000010101110101100101011111010110010100010101001100010011000100111101010111 (
b1 4
1$
#70000
0$
#75000
b1 1
1$
#80000
0$
#85000
b10 1
1$
#90000
0$
#95000
b10100100100010101000100 &
b0 "
b0 2
b1000001010011000100110001011111010100100100010101000100 (
b0 1
b10 4
1$
#100000
0$
#105000
b1 1
1$
#110000
0$
#115000
b100011101010010010001010100010101001110 '
b1 !
b1 3
b0 "
b0 2
b1010010010011110100000101000100010111110100011101010010010001010100010101001110 (
b0 1
b11 4
1$
#120000
0$
#125000
1$
#130000
0$
#135000
1$
#140000
0$
#145000
1$
#150000
0$
#155000
1$
#160000
0$
#165000
1$
#170000
0$
#175000
1$
#180000
0$
#185000
1$
#190000
0$
#195000
1$
#200000
0$
#205000
1$
#210000
0$
0%
#215000
b10110010100010101001100010011000100111101010111 '
b10 !
b10 3
b0 "
b0 2
b101001001001111010000010100010001011111010110010100010101001100010011000100111101010111 (
b100 4
1$
#220000
0$
#225000
b1 1
1$
#230000
0$
#235000
b10 1
1$
#240000
0$
#245000
b10100100100010101000100 '
b100011101010010010001010100010101001110 &
b0 !
b0 3
b1 "
b1 2
b10010000101011101011001010111110100011101010010010001010100010101001110 (
b0 1
b0 4
1$
#250000
0$
#255000
1$
#260000
0$
#265000
1$
#270000
0$
#275000
1$
#280000
0$
#285000
1$
#290000
0$
#295000
1$
#300000
0$
#305000
1$
#310000
0$
#315000
1$
#320000
0$
#325000
1$
#330000
0$
#335000
1$
#340000
0$
#345000
1$
#350000
0$
#355000
1$
#360000
0$
1%
#365000
b10110010100010101001100010011000100111101010111 &
b10 "
b10 2
b1001000010101110101100101011111010110010100010101001100010011000100111101010111 (
b1 4
1$
#370000
0$
#375000
b1 1
1$
#380000
0$
#385000
b10 1
1$
#390000
0$
#395000
b10100100100010101000100 &
b0 "
b0 2
b1000001010011000100110001011111010100100100010101000100 (
b0 1
b10 4
1$
#400000
0$
#405000
b1 1
1$
#410000
0$
0%
#415000
b100011101010010010001010100010101001110 '
b1 !
b1 3
b0 "
b0 2
b1010010010011110100000101000100010111110100011101010010010001010100010101001110 (
b0 1
b11 4
1$
#420000
0$
#425000
b10110010100010101001100010011000100111101010111 '
b10 !
b10 3
b0 "
b0 2
b101001001001111010000010100010001011111010110010100010101001100010011000100111101010111 (
b100 4
1$
#430000
0$
#435000
b1 1
1$
#440000
0$
#445000
b10 1
1$
#450000
0$
#455000
b10100100100010101000100 '
b100011101010010010001010100010101001110 &
b0 !
b0 3
b1 "
b1 2
b10010000101011101011001010111110100011101010010010001010100010101001110 (
b0 1
b0 4
1$
